{
	"tribe": "herald",
	"nameJP": "アリラト",
	"nameEN": "Alilat",
	"level": 84,
	"stats": {
		"hp": 441,
		"mp": 428,
		"strength": 77,
		"skill": 86,
		"magic": 112,
		"speed": 73,
		"luck": 104
	},
	"affinity": {
		"physical": "protect",
		"gun": "protect",
		"fire": "-",
		"ice": "-",
		"thunder": "-",
		"shock": "-",
		"banish": "null",
		"curse": "null",
		"bind": "null",
		"sleep": "null",
		"cold": "null",
		"confusion": "null",
		"poison": "null"
	},
	"skills": {
		"ディアラハン": 0,
		"メギドラオン": 0,
		"コンセントレイト": 85
	},
	"fusions": [
		["ペリ", "アズラエル", "イスラフィール"]
	]
}
